logstash_formatter/__init__.py
logstash_formatter/formatter.py
logstash_python_formatter-0.1.2.dist-info/LICENSE
logstash_python_formatter-0.1.2.dist-info/METADATA
logstash_python_formatter-0.1.2.dist-info/WHEEL
logstash_python_formatter-0.1.2.dist-info/top_level.txt
logstash_python_formatter-0.1.2.dist-info/RECORD
