Metadata-Version: 2.1
Name: logstash-python-formatter
Version: 0.1.2
Summary: Python formatter for working with Logstash json filters.
Home-page: https://github.com/mbarrientos/logstash-python-formatter
Author: Miguel Barrientos Fernández
Author-email: UNKNOWN
License: MIT
Keywords: python,logging,logstash_formatter,formatter,log
Platform: UNKNOWN
Classifier: Development Status :: 5 - Production/Stable
Classifier: Environment :: Web Environment
Classifier: Intended Audience :: Information Technology
Classifier: Intended Audience :: System Administrators
Classifier: Intended Audience :: Telecommunications Industry
Classifier: License :: OSI Approved :: MIT License
Classifier: Natural Language :: English
Classifier: Operating System :: MacOS :: MacOS X
Classifier: Operating System :: Microsoft :: Windows
Classifier: Operating System :: POSIX
Classifier: Programming Language :: Python
Classifier: Programming Language :: Python :: 2
Classifier: Programming Language :: Python :: 3
Classifier: Topic :: Software Development
Classifier: Topic :: Software Development :: Bug Tracking
Classifier: Topic :: System :: Logging
